{
  "version": 1,
  "publishedAt": "2026-05-14T09:29:46.860Z",
  "overrides": {
    "div[0]>div[0]>div[14]>button[0]#h:d901835d": "👁 הצג",
    "div[0]>div[0]>div[16]>section[0]>div[0]>div[1]>div[0]>h3[0]#h:a5c90c46": "צילום מקצועי",
    "div[0]>div[0]>div[16]>section[0]>div[0]>div[1]>div[0]>p[0]#h:dddfb300": "צילום מקצועי עם מספר מצלמות, סאונד נקי ואפילו מתאימים את התאורה לצבעי המותג שלכם,<br style=\"app-region: no-drag !important;\">ואתם יוצאים עם תוכן שנראה כמו תוכנית בנטפליקס.",
    "div[0]>div[0]>div[16]>section[0]>div[0]>div[1]>div[1]>p[0]#h:dddfb300": "כל פרק עובר עריכה מקצועית וקפדנית - חיתוכים, מוזיקה, ניתוב זוויות ועריכת צבע וסאונד.<br style=\"app-region: no-drag !important;\">פרק שתצלמו היום ימשיך להביא לקוחות גם עוד שנתיים.",
    "div[0]>div[0]>div[0]>section[0]>div[1]>div[0]>div[1]>h1[0]>span[0]#h:e82d681d": "הערכה לאחר תיקון"
  },
  "sectionOrder": null,
  "elementOffsets": {},
  "hiddenSections": [
    "how-it-works"
  ]
}